pinterest_scraper/__init__.py
pinterest_scraper/cli.py
pinterest_scraper/scraper.py
pinterest_scraper/utils.py
pinterest_scrapper-1.dist-info/licenses/LICENSE
pinterest_scrapper-1.dist-info/METADATA
pinterest_scrapper-1.dist-info/WHEEL
pinterest_scrapper-1.dist-info/entry_points.txt
pinterest_scrapper-1.dist-info/top_level.txt
pinterest_scrapper-1.dist-info/RECORD
