Metadata-Version: 2.4
Name: pinterest-scrapper
Version: 1
Summary: A Python package for scraping images from Pinterest
Home-page: https://github.com/hanspaa2017108/pinterest-scraper
Author: Aman Hanspal
Author-email: your.email@example.com
License-Expression: MIT
Project-URL: Homepage, https://github.com/hanspaa2017108/pinterest-scraper
Project-URL: Bug Tracker, https://github.com/hanspaa2017108/pinterest-scraper/issues
Keywords: pinterest,scraper,images,web scraping,playwright
Classifier: Development Status :: 3 - Alpha
Classifier: Intended Audience :: Developers
Classifier: Programming Language :: Python :: 3
Classifier: Programming Language :: Python :: 3.8
Classifier: Programming Language :: Python :: 3.9
Classifier: Programming Language :: Python :: 3.10
Classifier: Programming Language :: Python :: 3.11
Classifier: Topic :: Internet :: WWW/HTTP :: Browsers
Classifier: Topic :: Software Development :: Libraries :: Python Modules
Requires-Python: >=3.8
License-File: LICENSE
Requires-Dist: playwright>=1.30.0
Requires-Dist: aiohttp>=3.8.0
Requires-Dist: asyncio>=3.4.3
Provides-Extra: dev
Requires-Dist: pytest>=7.0.0; extra == "dev"
Requires-Dist: black>=23.0.0; extra == "dev"
Requires-Dist: flake8>=6.0.0; extra == "dev"
Dynamic: author-email
Dynamic: home-page
Dynamic: license-file
Dynamic: requires-python
